{
  "swagger": "2.0",
  "info": {
    "title": "github.com/grapery/grapery/common-protoc/service.proto",
    "version": "version not set"
  },
  "consumes": [
    "application/json"
  ],
  "produces": [
    "application/json"
  ],
  "paths": {
    "/v1/about": {
      "get": {
        "operationId": "About",
        "responses": {
          "200": {
            "description": "A successful response.",
            "schema": {
              "$ref": "#/definitions/apiAboutResponse"
            }
          }
        },
        "tags": [
          "TeamsAPI"
        ]
      }
    },
    "/v1/group": {
      "post": {
        "operationId": "CreateGroup",
        "responses": {
          "200": {
            "description": "A successful response.",
            "schema": {
              "$ref": "#/definitions/apiCreateGroupResponse"
            }
          }
        },
        "parameters": [
          {
            "name": "body",
            "in": "body",
            "required": true,
            "schema": {
              "$ref": "#/definitions/apiCreateGroupReqeust"
            }
          }
        ],
        "tags": [
          "TeamsAPI"
        ]
      }
    },
    "/v1/group/actives": {
      "post": {
        "operationId": "GetGroupActives",
        "responses": {
          "200": {
            "description": "A successful response.",
            "schema": {
              "$ref": "#/definitions/apiGetGroupActivesResponse"
            }
          }
        },
        "parameters": [
          {
            "name": "body",
            "in": "body",
            "required": true,
            "schema": {
              "$ref": "#/definitions/apiGetGroupActivesRequest"
            }
          }
        ],
        "tags": [
          "TeamsAPI"
        ]
      }
    },
    "/v1/group/info": {
      "post": {
        "operationId": "GetGroup",
        "responses": {
          "200": {
            "description": "A successful response.",
            "schema": {
              "$ref": "#/definitions/apiGetGroupResponse"
            }
          }
        },
        "parameters": [
          {
            "name": "body",
            "in": "body",
            "required": true,
            "schema": {
              "$ref": "#/definitions/apiGetGroupReqeust"
            }
          }
        ],
        "tags": [
          "TeamsAPI"
        ]
      }
    },
    "/v1/group/info/members": {
      "post": {
        "operationId": "FetchGroupMembers",
        "responses": {
          "200": {
            "description": "A successful response.",
            "schema": {
              "$ref": "#/definitions/apiFetchGroupMembersResponse"
            }
          }
        },
        "parameters": [
          {
            "name": "body",
            "in": "body",
            "required": true,
            "schema": {
              "$ref": "#/definitions/apiFetchGroupMembersRequest"
            }
          }
        ],
        "tags": [
          "TeamsAPI"
        ]
      }
    },
    "/v1/group/info/project": {
      "post": {
        "operationId": "CreateProject",
        "responses": {
          "200": {
            "description": "A successful response.",
            "schema": {
              "$ref": "#/definitions/apiCreateProjectResponse"
            }
          }
        },
        "parameters": [
          {
            "name": "body",
            "in": "body",
            "required": true,
            "schema": {
              "$ref": "#/definitions/apiCreateProjectRequest"
            }
          }
        ],
        "tags": [
          "TeamsAPI"
        ]
      }
    },
    "/v1/group/info/project/list": {
      "post": {
        "operationId": "GetProject",
        "responses": {
          "200": {
            "description": "A successful response.",
            "schema": {
              "$ref": "#/definitions/apiGetProjectResponse"
            }
          }
        },
        "parameters": [
          {
            "name": "body",
            "in": "body",
            "required": true,
            "schema": {
              "$ref": "#/definitions/apiGetProjectRequest"
            }
          }
        ],
        "tags": [
          "TeamsAPI"
        ]
      }
    },
    "/v1/group/info/project/profile": {
      "post": {
        "operationId": "GetProjectProfile",
        "responses": {
          "200": {
            "description": "A successful response.",
            "schema": {
              "$ref": "#/definitions/apiGetProjectProfileResponse"
            }
          }
        },
        "parameters": [
          {
            "name": "body",
            "in": "body",
            "required": true,
            "schema": {
              "$ref": "#/definitions/apiGetProjectProfileRequest"
            }
          }
        ],
        "tags": [
          "TeamsAPI"
        ]
      }
    },
    "/v1/group/info/project/remove": {
      "post": {
        "operationId": "DeleteProject",
        "responses": {
          "200": {
            "description": "A successful response.",
            "schema": {
              "$ref": "#/definitions/apiDeleteProjectResponse"
            }
          }
        },
        "parameters": [
          {
            "name": "body",
            "in": "body",
            "required": true,
            "schema": {
              "$ref": "#/definitions/apiDeleteProjectRequest"
            }
          }
        ],
        "tags": [
          "TeamsAPI"
        ]
      }
    },
    "/v1/group/info/project/unwatch": {
      "post": {
        "operationId": "UnWatchProject",
        "responses": {
          "200": {
            "description": "A successful response.",
            "schema": {
              "$ref": "#/definitions/apiUnWatchProjectResponse"
            }
          }
        },
        "parameters": [
          {
            "name": "body",
            "in": "body",
            "required": true,
            "schema": {
              "$ref": "#/definitions/apiUnWatchProjectReqeust"
            }
          }
        ],
        "tags": [
          "TeamsAPI"
        ]
      }
    },
    "/v1/group/info/project/update": {
      "post": {
        "operationId": "UpdateProjectProfile",
        "responses": {
          "200": {
            "description": "A successful response.",
            "schema": {
              "$ref": "#/definitions/apiUpdateProjectProfileResponse"
            }
          }
        },
        "parameters": [
          {
            "name": "body",
            "in": "body",
            "required": true,
            "schema": {
              "$ref": "#/definitions/apiUpdateProjectProfileRequest"
            }
          }
        ],
        "tags": [
          "TeamsAPI"
        ]
      }
    },
    "/v1/group/info/project/watch": {
      "post": {
        "operationId": "WatchProject",
        "responses": {
          "200": {
            "description": "A successful response.",
            "schema": {
              "$ref": "#/definitions/apiWatchProjectResponse"
            }
          }
        },
        "parameters": [
          {
            "name": "body",
            "in": "body",
            "required": true,
            "schema": {
              "$ref": "#/definitions/apiWatchProjectReqeust"
            }
          }
        ],
        "tags": [
          "TeamsAPI"
        ]
      }
    },
    "/v1/group/info/projects/search": {
      "post": {
        "operationId": "SearchGroupProject",
        "responses": {
          "200": {
            "description": "A successful response.",
            "schema": {
              "$ref": "#/definitions/apiSearchProjectResponse"
            }
          }
        },
        "parameters": [
          {
            "name": "body",
            "in": "body",
            "required": true,
            "schema": {
              "$ref": "#/definitions/apiSearchProjectRequest"
            }
          }
        ],
        "tags": [
          "TeamsAPI"
        ]
      }
    },
    "/v1/group/info/remove": {
      "post": {
        "operationId": "DeleteGroup",
        "responses": {
          "200": {
            "description": "A successful response.",
            "schema": {
              "$ref": "#/definitions/apiDeleteGroupResponse"
            }
          }
        },
        "parameters": [
          {
            "name": "body",
            "in": "body",
            "required": true,
            "schema": {
              "$ref": "#/definitions/apiDeleteGroupRequest"
            }
          }
        ],
        "tags": [
          "TeamsAPI"
        ]
      }
    },
    "/v1/group/info/update": {
      "post": {
        "operationId": "UpdateGroupInfo",
        "responses": {
          "200": {
            "description": "A successful response.",
            "schema": {
              "$ref": "#/definitions/apiUpdateGroupInfoResponse"
            }
          }
        },
        "parameters": [
          {
            "name": "body",
            "in": "body",
            "required": true,
            "schema": {
              "$ref": "#/definitions/apiUpdateGroupInfoRequest"
            }
          }
        ],
        "tags": [
          "TeamsAPI"
        ]
      }
    },
    "/v1/group/items": {
      "post": {
        "operationId": "GetGroupItems",
        "responses": {
          "200": {
            "description": "A successful response.",
            "schema": {
              "$ref": "#/definitions/apiGetGroupItemsResponse"
            }
          }
        },
        "parameters": [
          {
            "name": "body",
            "in": "body",
            "required": true,
            "schema": {
              "$ref": "#/definitions/apiGetGroupItemsRequest"
            }
          }
        ],
        "tags": [
          "TeamsAPI"
        ]
      }
    },
    "/v1/group/join": {
      "post": {
        "operationId": "JoinGroup",
        "responses": {
          "200": {
            "description": "A successful response.",
            "schema": {
              "$ref": "#/definitions/apiJoinGroupResponse"
            }
          }
        },
        "parameters": [
          {
            "name": "body",
            "in": "body",
            "required": true,
            "schema": {
              "$ref": "#/definitions/apiJoinGroupRequest"
            }
          }
        ],
        "tags": [
          "TeamsAPI"
        ]
      }
    },
    "/v1/group/leave": {
      "post": {
        "operationId": "LeaveGroup",
        "responses": {
          "200": {
            "description": "A successful response.",
            "schema": {
              "$ref": "#/definitions/apiLeaveGroupResponse"
            }
          }
        },
        "parameters": [
          {
            "name": "body",
            "in": "body",
            "required": true,
            "schema": {
              "$ref": "#/definitions/apiLeaveGroupRequest"
            }
          }
        ],
        "tags": [
          "TeamsAPI"
        ]
      }
    },
    "/v1/group/project/comment/list": {
      "post": {
        "operationId": "GetGroupItemComment",
        "responses": {
          "200": {
            "description": "A successful response.",
            "schema": {
              "$ref": "#/definitions/apiGetUserProjectCommentResp"
            }
          }
        },
        "parameters": [
          {
            "name": "body",
            "in": "body",
            "required": true,
            "schema": {
              "$ref": "#/definitions/apiGetUserProjectCommentReq"
            }
          }
        ],
        "tags": [
          "TeamsAPI"
        ]
      }
    },
    "/v1/group/project/info/items": {
      "post": {
        "operationId": "GetProjectItems",
        "responses": {
          "200": {
            "description": "A successful response.",
            "schema": {
              "$ref": "#/definitions/apiGetProjectItemsResponse"
            }
          }
        },
        "parameters": [
          {
            "name": "body",
            "in": "body",
            "required": true,
            "schema": {
              "$ref": "#/definitions/apiGetProjectItemsRequest"
            }
          }
        ],
        "tags": [
          "TeamsAPI"
        ]
      }
    },
    "/v1/group/project/item/add": {
      "post": {
        "operationId": "CreateItem",
        "responses": {
          "200": {
            "description": "A successful response.",
            "schema": {
              "$ref": "#/definitions/apiCreateItemResponse"
            }
          }
        },
        "parameters": [
          {
            "name": "body",
            "in": "body",
            "required": true,
            "schema": {
              "$ref": "#/definitions/apiCreateItemRequest"
            }
          }
        ],
        "tags": [
          "TeamsAPI"
        ]
      }
    },
    "/v1/group/project/item/comment/add": {
      "post": {
        "operationId": "CreateComment",
        "responses": {
          "200": {
            "description": "A successful response.",
            "schema": {
              "$ref": "#/definitions/apiCreateCommentResp"
            }
          }
        },
        "parameters": [
          {
            "name": "body",
            "in": "body",
            "required": true,
            "schema": {
              "$ref": "#/definitions/apiCreateCommentReq"
            }
          }
        ],
        "tags": [
          "TeamsAPI"
        ]
      }
    },
    "/v1/group/project/item/comment/list": {
      "post": {
        "operationId": "GetItemComment",
        "responses": {
          "200": {
            "description": "A successful response.",
            "schema": {
              "$ref": "#/definitions/apiGetItemCommentResp"
            }
          }
        },
        "parameters": [
          {
            "name": "body",
            "in": "body",
            "required": true,
            "schema": {
              "$ref": "#/definitions/apiGetItemCommentReq"
            }
          }
        ],
        "tags": [
          "TeamsAPI"
        ]
      }
    },
    "/v1/group/project/item/info": {
      "post": {
        "operationId": "GetItem",
        "responses": {
          "200": {
            "description": "A successful response.",
            "schema": {
              "$ref": "#/definitions/apiGetItemResponse"
            }
          }
        },
        "parameters": [
          {
            "name": "body",
            "in": "body",
            "required": true,
            "schema": {
              "$ref": "#/definitions/apiGetItemRequest"
            }
          }
        ],
        "tags": [
          "TeamsAPI"
        ]
      }
    },
    "/v1/group/project/item/like": {
      "post": {
        "operationId": "LikeItem",
        "responses": {
          "200": {
            "description": "A successful response.",
            "schema": {
              "$ref": "#/definitions/apiLikeItemResponse"
            }
          }
        },
        "parameters": [
          {
            "name": "body",
            "in": "body",
            "required": true,
            "schema": {
              "$ref": "#/definitions/apiLikeItemRequest"
            }
          }
        ],
        "tags": [
          "TeamsAPI"
        ]
      }
    },
    "/v1/group/project/item/remove": {
      "post": {
        "operationId": "DeleteItem",
        "responses": {
          "200": {
            "description": "A successful response.",
            "schema": {
              "$ref": "#/definitions/apiDeleteItemResponse"
            }
          }
        },
        "parameters": [
          {
            "name": "body",
            "in": "body",
            "required": true,
            "schema": {
              "$ref": "#/definitions/apiDeleteItemRequest"
            }
          }
        ],
        "tags": [
          "TeamsAPI"
        ]
      }
    },
    "/v1/group/project/item/update": {
      "post": {
        "operationId": "UpdateItem",
        "responses": {
          "200": {
            "description": "A successful response.",
            "schema": {
              "$ref": "#/definitions/apiUpdateItemResponse"
            }
          }
        },
        "parameters": [
          {
            "name": "body",
            "in": "body",
            "required": true,
            "schema": {
              "$ref": "#/definitions/apiUpdateItemRequest"
            }
          }
        ],
        "tags": [
          "TeamsAPI"
        ]
      }
    },
    "/v1/group/projects": {
      "post": {
        "operationId": "FetchGroupProjects",
        "responses": {
          "200": {
            "description": "A successful response.",
            "schema": {
              "$ref": "#/definitions/apiFetchGroupProjectsResponse"
            }
          }
        },
        "parameters": [
          {
            "name": "body",
            "in": "body",
            "required": true,
            "schema": {
              "$ref": "#/definitions/apiFetchGroupProjectsReqeust"
            }
          }
        ],
        "tags": [
          "TeamsAPI"
        ]
      }
    },
    "/v1/group/search": {
      "post": {
        "operationId": "SearchGroup",
        "responses": {
          "200": {
            "description": "A successful response.",
            "schema": {
              "$ref": "#/definitions/apiSearchGroupResponse"
            }
          }
        },
        "parameters": [
          {
            "name": "body",
            "in": "body",
            "required": true,
            "schema": {
              "$ref": "#/definitions/apiSearchGroupReqeust"
            }
          }
        ],
        "tags": [
          "TeamsAPI"
        ]
      }
    },
    "/v1/logout": {
      "post": {
        "operationId": "Logout",
        "responses": {
          "200": {
            "description": "A successful response.",
            "schema": {
              "$ref": "#/definitions/apiLogoutResponse"
            }
          }
        },
        "parameters": [
          {
            "name": "body",
            "in": "body",
            "required": true,
            "schema": {
              "$ref": "#/definitions/apiLogoutRequest"
            }
          }
        ],
        "tags": [
          "TeamsAPI"
        ]
      }
    },
    "/v1/projects/explore": {
      "post": {
        "operationId": "ExploreProject",
        "responses": {
          "200": {
            "description": "A successful response.",
            "schema": {
              "$ref": "#/definitions/apiExploreProjectsResponse"
            }
          }
        },
        "parameters": [
          {
            "name": "body",
            "in": "body",
            "required": true,
            "schema": {
              "$ref": "#/definitions/apiExploreProjectsRequest"
            }
          }
        ],
        "tags": [
          "TeamsAPI"
        ]
      }
    },
    "/v1/projects/search": {
      "post": {
        "operationId": "SearchProject",
        "responses": {
          "200": {
            "description": "A successful response.",
            "schema": {
              "$ref": "#/definitions/apiSearchAllProjectResponse"
            }
          }
        },
        "parameters": [
          {
            "name": "body",
            "in": "body",
            "required": true,
            "schema": {
              "$ref": "#/definitions/apiSearchAllProjectRequest"
            }
          }
        ],
        "tags": [
          "TeamsAPI"
        ]
      }
    },
    "/v1/register": {
      "post": {
        "operationId": "Register",
        "responses": {
          "200": {
            "description": "A successful response.",
            "schema": {
              "$ref": "#/definitions/apiRegisterResponse"
            }
          }
        },
        "parameters": [
          {
            "name": "body",
            "in": "body",
            "required": true,
            "schema": {
              "$ref": "#/definitions/apiRegisterRequest"
            }
          }
        ],
        "tags": [
          "TeamsAPI"
        ]
      }
    },
    "/v1/reset/pwd": {
      "post": {
        "operationId": "ResetPwd",
        "responses": {
          "200": {
            "description": "A successful response.",
            "schema": {
              "$ref": "#/definitions/apiResetPasswordResponse"
            }
          }
        },
        "parameters": [
          {
            "name": "body",
            "in": "body",
            "required": true,
            "schema": {
              "$ref": "#/definitions/apiResetPasswordRequest"
            }
          }
        ],
        "tags": [
          "TeamsAPI"
        ]
      }
    },
    "/v1/user/actives": {
      "post": {
        "operationId": "FetchUserActives",
        "responses": {
          "200": {
            "description": "A successful response.",
            "schema": {
              "$ref": "#/definitions/apiFetchUserActivesResponse"
            }
          }
        },
        "parameters": [
          {
            "name": "body",
            "in": "body",
            "required": true,
            "schema": {
              "$ref": "#/definitions/apiFetchUserActivesRequest"
            }
          }
        ],
        "tags": [
          "TeamsAPI"
        ]
      }
    },
    "/v1/user/info": {
      "post": {
        "operationId": "UserInfo",
        "responses": {
          "200": {
            "description": "A successful response.",
            "schema": {
              "$ref": "#/definitions/apiUserInfoResponse"
            }
          }
        },
        "parameters": [
          {
            "name": "body",
            "in": "body",
            "required": true,
            "schema": {
              "$ref": "#/definitions/apiUserInfoRequest"
            }
          }
        ],
        "tags": [
          "TeamsAPI"
        ]
      }
    },
    "/v1/user/info/avator": {
      "post": {
        "operationId": "UpdateUserAvator",
        "responses": {
          "200": {
            "description": "A successful response.",
            "schema": {
              "$ref": "#/definitions/apiUpdateUserAvatorResponse"
            }
          }
        },
        "parameters": [
          {
            "name": "body",
            "in": "body",
            "required": true,
            "schema": {
              "$ref": "#/definitions/apiUpdateUserAvatorRequest"
            }
          }
        ],
        "tags": [
          "TeamsAPI"
        ]
      }
    },
    "/v1/user/info/groups": {
      "post": {
        "operationId": "UserGroup",
        "responses": {
          "200": {
            "description": "A successful response.",
            "schema": {
              "$ref": "#/definitions/apiUserGroupResponse"
            }
          }
        },
        "parameters": [
          {
            "name": "body",
            "in": "body",
            "required": true,
            "schema": {
              "$ref": "#/definitions/apiUserGroupRequest"
            }
          }
        ],
        "tags": [
          "TeamsAPI"
        ]
      }
    },
    "/v1/user/info/groups/following": {
      "post": {
        "operationId": "UserFollowingGroup",
        "responses": {
          "200": {
            "description": "A successful response.",
            "schema": {
              "$ref": "#/definitions/apiUserFollowingGroupResponse"
            }
          }
        },
        "parameters": [
          {
            "name": "body",
            "in": "body",
            "required": true,
            "schema": {
              "$ref": "#/definitions/apiUserFollowingGroupRequest"
            }
          }
        ],
        "tags": [
          "TeamsAPI"
        ]
      }
    },
    "/v1/user/info/update": {
      "post": {
        "operationId": "UserUpdate",
        "responses": {
          "200": {
            "description": "A successful response.",
            "schema": {
              "$ref": "#/definitions/apiUserUpdateResponse"
            }
          }
        },
        "parameters": [
          {
            "name": "body",
            "in": "body",
            "required": true,
            "schema": {
              "$ref": "#/definitions/apiUserUpdateRequest"
            }
          }
        ],
        "tags": [
          "TeamsAPI"
        ]
      }
    },
    "/v1/user/info/watching": {
      "post": {
        "operationId": "UserWatching",
        "responses": {
          "200": {
            "description": "A successful response.",
            "schema": {
              "$ref": "#/definitions/apiUserWatchingResponse"
            }
          }
        },
        "parameters": [
          {
            "name": "body",
            "in": "body",
            "required": true,
            "schema": {
              "$ref": "#/definitions/apiUserWatchingRequest"
            }
          }
        ],
        "tags": [
          "TeamsAPI"
        ]
      }
    },
    "/v1/user/items": {
      "post": {
        "operationId": "GetUserItems",
        "responses": {
          "200": {
            "description": "A successful response.",
            "schema": {
              "$ref": "#/definitions/apiGetUserItemsResponse"
            }
          }
        },
        "parameters": [
          {
            "name": "body",
            "in": "body",
            "required": true,
            "schema": {
              "$ref": "#/definitions/apiGetUserItemsRequest"
            }
          }
        ],
        "tags": [
          "TeamsAPI"
        ]
      }
    },
    "/v1/users/search": {
      "post": {
        "operationId": "SearchUser",
        "responses": {
          "200": {
            "description": "A successful response.",
            "schema": {
              "$ref": "#/definitions/apiSearchUserResponse"
            }
          }
        },
        "parameters": [
          {
            "name": "body",
            "in": "body",
            "required": true,
            "schema": {
              "$ref": "#/definitions/apiSearchUserRequest"
            }
          }
        ],
        "tags": [
          "TeamsAPI"
        ]
      }
    },
    "/v1/version": {
      "get": {
        "operationId": "Version",
        "responses": {
          "200": {
            "description": "A successful response.",
            "schema": {
              "$ref": "#/definitions/apiVersionResponse"
            }
          }
        },
        "tags": [
          "TeamsAPI"
        ]
      }
    }
  },
  "definitions": {
    "apiAboutResponse": {
      "type": "object",
      "properties": {
        "content": {
          "type": "string"
        }
      }
    },
    "apiActiveInfo": {
      "type": "object",
      "properties": {
        "user": {
          "$ref": "#/definitions/apiUserInfo"
        },
        "activeType": {
          "$ref": "#/definitions/apiActiveType"
        },
        "itemInfo": {
          "$ref": "#/definitions/apiItemInfo"
        },
        "projectInfo": {
          "$ref": "#/definitions/apiProjectInfo"
        },
        "groupInfo": {
          "$ref": "#/definitions/apiGroupInfo"
        }
      }
    },
    "apiActiveType": {
      "type": "string",
      "enum": [
        "AllActive",
        "Like",
        "Share",
        "Comment",
        "Collect",
        "DisAgree"
      ],
      "default": "AllActive"
    },
    "apiCreateCommentReq": {
      "type": "object",
      "properties": {
        "group_id": {
          "type": "integer",
          "format": "int32"
        },
        "item_id": {
          "type": "integer",
          "format": "int32"
        }
      }
    },
    "apiCreateCommentResp": {
      "type": "object"
    },
    "apiCreateGroupReqeust": {
      "type": "object",
      "properties": {
        "user_id": {
          "type": "string",
          "format": "uint64"
        },
        "name": {
          "type": "string"
        }
      }
    },
    "apiCreateGroupResponse": {
      "type": "object",
      "properties": {
        "info": {
          "$ref": "#/definitions/apiGroupInfo"
        }
      }
    },
    "apiCreateItemRequest": {
      "type": "object",
      "properties": {
        "group_id": {
          "type": "string",
          "format": "uint64"
        },
        "project_id": {
          "type": "string",
          "format": "uint64"
        },
        "name": {
          "type": "string"
        },
        "atype": {
          "$ref": "#/definitions/apiActiveType"
        },
        "user_id": {
          "type": "string",
          "format": "uint64"
        }
      }
    },
    "apiCreateItemResponse": {
      "type": "object",
      "properties": {
        "info": {
          "$ref": "#/definitions/apiItemInfo"
        }
      }
    },
    "apiCreateProjectRequest": {
      "type": "object",
      "properties": {
        "group_id": {
          "type": "string",
          "format": "uint64"
        },
        "name": {
          "type": "string"
        }
      }
    },
    "apiCreateProjectResponse": {
      "type": "object",
      "properties": {
        "info": {
          "$ref": "#/definitions/apiProjectInfo"
        }
      }
    },
    "apiDeleteGroupRequest": {
      "type": "object",
      "properties": {
        "group_id": {
          "type": "string",
          "format": "uint64"
        },
        "user_id": {
          "type": "string",
          "format": "uint64"
        }
      }
    },
    "apiDeleteGroupResponse": {
      "type": "object"
    },
    "apiDeleteItemRequest": {
      "type": "object",
      "properties": {
        "group_id": {
          "type": "string",
          "format": "uint64"
        },
        "project_id": {
          "type": "string",
          "format": "uint64"
        },
        "item_id": {
          "type": "string",
          "format": "uint64"
        },
        "user_id": {
          "type": "string",
          "format": "uint64"
        }
      }
    },
    "apiDeleteItemResponse": {
      "type": "object"
    },
    "apiDeleteProjectRequest": {
      "type": "object",
      "properties": {
        "group_id": {
          "type": "string",
          "format": "uint64"
        },
        "project_id": {
          "type": "string",
          "format": "uint64"
        },
        "user_id": {
          "type": "string",
          "format": "uint64"
        }
      }
    },
    "apiDeleteProjectResponse": {
      "type": "object"
    },
    "apiExploreProjectsRequest": {
      "type": "object",
      "properties": {
        "user_id": {
          "type": "string",
          "format": "uint64"
        },
        "group_id": {
          "type": "string",
          "format": "uint64"
        },
        "offset": {
          "type": "string",
          "format": "uint64"
        },
        "number": {
          "type": "string",
          "format": "uint64"
        }
      }
    },
    "apiExploreProjectsResponse": {
      "type": "object",
      "properties": {
        "user_id": {
          "type": "string",
          "format": "uint64"
        },
        "list": {
          "type": "array",
          "items": {
            "$ref": "#/definitions/apiProjectInfo"
          }
        },
        "offset": {
          "type": "string",
          "format": "uint64"
        },
        "number": {
          "type": "string",
          "format": "uint64"
        }
      }
    },
    "apiFetchGroupMembersRequest": {
      "type": "object",
      "properties": {
        "group_id": {
          "type": "string",
          "format": "uint64"
        },
        "offset": {
          "type": "string",
          "format": "uint64"
        },
        "number": {
          "type": "string",
          "format": "uint64"
        }
      }
    },
    "apiFetchGroupMembersResponse": {
      "type": "object",
      "properties": {
        "list": {
          "type": "array",
          "items": {
            "$ref": "#/definitions/apiUserInfo"
          }
        },
        "offset": {
          "type": "string",
          "format": "uint64"
        },
        "total": {
          "type": "string",
          "format": "uint64"
        }
      }
    },
    "apiFetchGroupProjectsReqeust": {
      "type": "object",
      "properties": {
        "group_id": {
          "type": "string",
          "format": "uint64"
        },
        "offset": {
          "type": "string",
          "format": "uint64"
        },
        "number": {
          "type": "string",
          "format": "uint64"
        }
      }
    },
    "apiFetchGroupProjectsResponse": {
      "type": "object",
      "properties": {
        "list": {
          "type": "array",
          "items": {
            "$ref": "#/definitions/apiProjectInfo"
          }
        },
        "offset": {
          "type": "string",
          "format": "uint64"
        },
        "number": {
          "type": "string",
          "format": "uint64"
        }
      }
    },
    "apiFetchUserActivesRequest": {
      "type": "object",
      "properties": {
        "user_id": {
          "type": "string",
          "format": "uint64"
        },
        "atype": {
          "$ref": "#/definitions/apiActiveType"
        }
      }
    },
    "apiFetchUserActivesResponse": {
      "type": "object",
      "properties": {
        "list": {
          "type": "array",
          "items": {
            "$ref": "#/definitions/apiActiveInfo"
          }
        }
      }
    },
    "apiGetGroupActivesRequest": {
      "type": "object",
      "properties": {
        "group_id": {
          "type": "string",
          "format": "uint64"
        },
        "atype": {
          "$ref": "#/definitions/apiActiveType"
        },
        "offset": {
          "type": "string",
          "format": "uint64"
        },
        "number": {
          "type": "string",
          "format": "uint64"
        }
      }
    },
    "apiGetGroupActivesResponse": {
      "type": "object",
      "properties": {
        "list": {
          "type": "array",
          "items": {
            "$ref": "#/definitions/apiActiveInfo"
          }
        },
        "offset": {
          "type": "string",
          "format": "uint64"
        },
        "number": {
          "type": "string",
          "format": "uint64"
        }
      }
    },
    "apiGetGroupItemsRequest": {
      "type": "object",
      "properties": {
        "group_id": {
          "type": "string",
          "format": "uint64"
        },
        "user_id": {
          "type": "string",
          "format": "uint64"
        },
        "offset": {
          "type": "string",
          "format": "uint64"
        },
        "number": {
          "type": "string",
          "format": "uint64"
        }
      }
    },
    "apiGetGroupItemsResponse": {
      "type": "object",
      "properties": {
        "list": {
          "type": "array",
          "items": {
            "$ref": "#/definitions/apiItemInfo"
          }
        },
        "group_id": {
          "type": "string",
          "format": "uint64"
        },
        "user_id": {
          "type": "string",
          "format": "uint64"
        },
        "offset": {
          "type": "string",
          "format": "uint64"
        },
        "number": {
          "type": "string",
          "format": "uint64"
        }
      }
    },
    "apiGetGroupReqeust": {
      "type": "object",
      "properties": {
        "group_id": {
          "type": "string",
          "format": "uint64"
        },
        "user_id": {
          "type": "string",
          "format": "uint64"
        },
        "name": {
          "type": "string"
        }
      }
    },
    "apiGetGroupResponse": {
      "type": "object",
      "properties": {
        "info": {
          "$ref": "#/definitions/apiGroupInfo"
        }
      }
    },
    "apiGetItemCommentReq": {
      "type": "object",
      "properties": {
        "group_id": {
          "type": "integer",
          "format": "int32"
        },
        "item_id": {
          "type": "integer",
          "format": "int32"
        }
      }
    },
    "apiGetItemCommentResp": {
      "type": "object"
    },
    "apiGetItemRequest": {
      "type": "object",
      "properties": {
        "group_id": {
          "type": "string",
          "format": "uint64"
        },
        "project_id": {
          "type": "string",
          "format": "uint64"
        },
        "item_id": {
          "type": "string",
          "format": "uint64"
        },
        "user_id": {
          "type": "string",
          "format": "uint64"
        }
      }
    },
    "apiGetItemResponse": {
      "type": "object",
      "properties": {
        "info": {
          "$ref": "#/definitions/apiItemInfo"
        }
      }
    },
    "apiGetProjectItemsRequest": {
      "type": "object",
      "properties": {
        "group_id": {
          "type": "string",
          "format": "uint64"
        },
        "project_id": {
          "type": "string",
          "format": "uint64"
        },
        "user_id": {
          "type": "string",
          "format": "uint64"
        },
        "offset": {
          "type": "string",
          "format": "uint64"
        },
        "number": {
          "type": "string",
          "format": "uint64"
        }
      }
    },
    "apiGetProjectItemsResponse": {
      "type": "object",
      "properties": {
        "list": {
          "type": "array",
          "items": {
            "$ref": "#/definitions/apiItemInfo"
          }
        },
        "group_id": {
          "type": "string",
          "format": "uint64"
        },
        "project_id": {
          "type": "string",
          "format": "uint64"
        },
        "user_id": {
          "type": "string",
          "format": "uint64"
        },
        "offset": {
          "type": "string",
          "format": "uint64"
        },
        "number": {
          "type": "string",
          "format": "uint64"
        }
      }
    },
    "apiGetProjectProfileRequest": {
      "type": "object",
      "properties": {
        "group_id": {
          "type": "string",
          "format": "uint64"
        },
        "project_id": {
          "type": "string",
          "format": "uint64"
        },
        "user_id": {
          "type": "string",
          "format": "uint64"
        }
      }
    },
    "apiGetProjectProfileResponse": {
      "type": "object",
      "properties": {
        "group_id": {
          "type": "string",
          "format": "uint64"
        },
        "project_id": {
          "type": "string",
          "format": "uint64"
        },
        "user_id": {
          "type": "string",
          "format": "uint64"
        },
        "info": {
          "$ref": "#/definitions/apiProjectProfileInfo"
        }
      }
    },
    "apiGetProjectRequest": {
      "type": "object",
      "properties": {
        "group_id": {
          "type": "string",
          "format": "uint64"
        },
        "project_id": {
          "type": "string",
          "format": "uint64"
        },
        "user_id": {
          "type": "string",
          "format": "uint64"
        }
      }
    },
    "apiGetProjectResponse": {
      "type": "object",
      "properties": {
        "info": {
          "$ref": "#/definitions/apiProjectInfo"
        }
      }
    },
    "apiGetUserItemsRequest": {
      "type": "object",
      "properties": {
        "user_id": {
          "type": "string",
          "format": "uint64"
        },
        "offset": {
          "type": "string",
          "format": "uint64"
        },
        "number": {
          "type": "string",
          "format": "uint64"
        }
      }
    },
    "apiGetUserItemsResponse": {
      "type": "object",
      "properties": {
        "list": {
          "type": "array",
          "items": {
            "$ref": "#/definitions/apiItemInfo"
          }
        },
        "user_id": {
          "type": "string",
          "format": "uint64"
        },
        "offset": {
          "type": "string",
          "format": "uint64"
        },
        "number": {
          "type": "string",
          "format": "uint64"
        }
      }
    },
    "apiGetUserProjectCommentReq": {
      "type": "object"
    },
    "apiGetUserProjectCommentResp": {
      "type": "object"
    },
    "apiGroupInfo": {
      "type": "object",
      "properties": {
        "group_id": {
          "type": "string",
          "format": "uint64"
        },
        "name": {
          "type": "string"
        },
        "avatar": {
          "type": "string"
        },
        "desc": {
          "type": "string"
        },
        "creator": {
          "$ref": "#/definitions/apiUserInfo"
        },
        "owner": {
          "$ref": "#/definitions/apiUserInfo"
        },
        "tags": {
          "type": "array",
          "items": {
            "$ref": "#/definitions/apiTags"
          }
        }
      }
    },
    "apiItemDetail": {
      "type": "object",
      "properties": {
        "word": {
          "$ref": "#/definitions/apiWordDetail"
        },
        "pictures": {
          "$ref": "#/definitions/apiPictureDetail"
        },
        "video": {
          "$ref": "#/definitions/apiVideoDetail"
        },
        "music": {
          "$ref": "#/definitions/apiMusicShareDetail"
        },
        "voice": {
          "$ref": "#/definitions/apiVoiceDetail"
        },
        "share": {
          "$ref": "#/definitions/apiShareDetail"
        }
      }
    },
    "apiItemInfo": {
      "type": "object",
      "properties": {
        "group_id": {
          "type": "string",
          "format": "uint64"
        },
        "project_id": {
          "type": "string",
          "format": "uint64"
        },
        "user_id": {
          "type": "string",
          "format": "uint64"
        },
        "title": {
          "type": "string"
        },
        "content": {
          "$ref": "#/definitions/apiItemDetail"
        },
        "itype": {
          "$ref": "#/definitions/apiItemType"
        }
      }
    },
    "apiItemType": {
      "type": "string",
      "enum": [
        "AllItem",
        "ShortWord",
        "Paper",
        "Picture",
        "Video",
        "Music",
        "Link",
        "Location"
      ],
      "default": "AllItem"
    },
    "apiJoinGroupRequest": {
      "type": "object",
      "properties": {
        "group_id": {
          "type": "string",
          "format": "uint64"
        },
        "user_id": {
          "type": "string",
          "format": "uint64"
        }
      }
    },
    "apiJoinGroupResponse": {
      "type": "object"
    },
    "apiLeaveGroupRequest": {
      "type": "object",
      "properties": {
        "group_id": {
          "type": "string",
          "format": "uint64"
        },
        "user_id": {
          "type": "string",
          "format": "uint64"
        }
      }
    },
    "apiLeaveGroupResponse": {
      "type": "object"
    },
    "apiLikeItemRequest": {
      "type": "object",
      "properties": {
        "group_id": {
          "type": "string",
          "format": "uint64"
        },
        "project_id": {
          "type": "string",
          "format": "uint64"
        },
        "item_id": {
          "type": "string",
          "format": "uint64"
        },
        "user_id": {
          "type": "string",
          "format": "uint64"
        },
        "islike": {
          "type": "boolean",
          "format": "boolean"
        }
      }
    },
    "apiLikeItemResponse": {
      "type": "object"
    },
    "apiLogoutRequest": {
      "type": "object",
      "properties": {
        "user_id": {
          "type": "string",
          "format": "uint64"
        },
        "token": {
          "type": "string"
        }
      }
    },
    "apiLogoutResponse": {
      "type": "object"
    },
    "apiMusicShareDetail": {
      "type": "object",
      "properties": {
        "resourceUrl": {
          "type": "string"
        },
        "source": {
          "type": "string",
          "format": "uint64"
        }
      }
    },
    "apiPictureDetail": {
      "type": "object",
      "properties": {
        "list": {
          "type": "array",
          "items": {
            "$ref": "#/definitions/apiPictureInfo"
          }
        },
        "num": {
          "type": "string",
          "format": "uint64"
        }
      }
    },
    "apiPictureInfo": {
      "type": "object",
      "properties": {
        "resource_url": {
          "type": "string"
        },
        "size": {
          "type": "string",
          "format": "uint64"
        }
      }
    },
    "apiProjectInfo": {
      "type": "object",
      "properties": {
        "project_id": {
          "type": "string",
          "format": "uint64"
        },
        "group_id": {
          "type": "integer",
          "format": "int64"
        },
        "name": {
          "type": "string"
        },
        "avatar": {
          "type": "string"
        },
        "creator": {
          "$ref": "#/definitions/apiUserInfo"
        },
        "owner": {
          "$ref": "#/definitions/apiUserInfo"
        },
        "tags": {
          "type": "array",
          "items": {
            "$ref": "#/definitions/apiTags"
          }
        },
        "visable": {
          "$ref": "#/definitions/apiVisibleType"
        },
        "isAchieve": {
          "type": "boolean",
          "format": "boolean"
        },
        "isClose": {
          "type": "boolean",
          "format": "boolean"
        }
      }
    },
    "apiProjectProfileInfo": {
      "type": "object",
      "properties": {
        "project_id": {
          "type": "string",
          "format": "uint64"
        },
        "group_id": {
          "type": "integer",
          "format": "int64"
        },
        "Description": {
          "type": "string"
        },
        "WatchingCount": {
          "type": "string",
          "format": "uint64"
        },
        "InvolvedCount": {
          "type": "string",
          "format": "uint64"
        },
        "Avatar": {
          "type": "string"
        },
        "visable": {
          "$ref": "#/definitions/apiVisibleType"
        },
        "isAchieve": {
          "type": "boolean",
          "format": "boolean"
        },
        "isClose": {
          "type": "boolean",
          "format": "boolean"
        },
        "isPrivate": {
          "type": "boolean",
          "format": "boolean"
        }
      }
    },
    "apiRegisterRequest": {
      "type": "object",
      "properties": {
        "account": {
          "type": "string"
        },
        "password": {
          "type": "string"
        }
      }
    },
    "apiRegisterResponse": {
      "type": "object",
      "properties": {
        "status": {
          "type": "integer",
          "format": "int32"
        }
      }
    },
    "apiResetPasswordRequest": {
      "type": "object",
      "properties": {
        "account": {
          "type": "string"
        },
        "oldPwd": {
          "type": "string"
        },
        "newPwd": {
          "type": "string"
        }
      }
    },
    "apiResetPasswordResponse": {
      "type": "object",
      "properties": {
        "account": {
          "type": "string"
        },
        "status": {
          "type": "string",
          "format": "int64"
        }
      }
    },
    "apiSearchAllProjectRequest": {
      "type": "object",
      "properties": {
        "user_id": {
          "type": "string",
          "format": "uint64"
        },
        "name": {
          "type": "string"
        },
        "offset": {
          "type": "string",
          "format": "uint64"
        },
        "number": {
          "type": "string",
          "format": "uint64"
        }
      }
    },
    "apiSearchAllProjectResponse": {
      "type": "object",
      "properties": {
        "user_id": {
          "type": "string",
          "format": "uint64"
        },
        "list": {
          "type": "array",
          "items": {
            "$ref": "#/definitions/apiProjectInfo"
          }
        },
        "offset": {
          "type": "string",
          "format": "uint64"
        },
        "number": {
          "type": "string",
          "format": "uint64"
        }
      }
    },
    "apiSearchGroupReqeust": {
      "type": "object",
      "properties": {
        "name": {
          "type": "string"
        }
      }
    },
    "apiSearchGroupResponse": {
      "type": "object",
      "properties": {
        "list": {
          "type": "array",
          "items": {
            "$ref": "#/definitions/apiGroupInfo"
          }
        },
        "offset": {
          "type": "string",
          "format": "uint64"
        },
        "number": {
          "type": "string",
          "format": "uint64"
        }
      }
    },
    "apiSearchProjectRequest": {
      "type": "object",
      "properties": {
        "group_id": {
          "type": "string",
          "format": "uint64"
        },
        "name": {
          "type": "string"
        },
        "offset": {
          "type": "string",
          "format": "uint64"
        },
        "number": {
          "type": "string",
          "format": "uint64"
        }
      }
    },
    "apiSearchProjectResponse": {
      "type": "object",
      "properties": {
        "group_id": {
          "type": "string",
          "format": "uint64"
        },
        "list": {
          "type": "array",
          "items": {
            "$ref": "#/definitions/apiProjectInfo"
          }
        },
        "offset": {
          "type": "string",
          "format": "uint64"
        },
        "number": {
          "type": "string",
          "format": "uint64"
        }
      }
    },
    "apiSearchUserRequest": {
      "type": "object",
      "properties": {
        "name": {
          "type": "string"
        },
        "group_id": {
          "type": "string",
          "format": "uint64"
        },
        "offset": {
          "type": "string",
          "format": "uint64"
        },
        "number": {
          "type": "string",
          "format": "uint64"
        }
      }
    },
    "apiSearchUserResponse": {
      "type": "object",
      "properties": {
        "list": {
          "type": "array",
          "items": {
            "$ref": "#/definitions/apiUserInfo"
          }
        },
        "offset": {
          "type": "string",
          "format": "uint64"
        },
        "number": {
          "type": "string",
          "format": "uint64"
        }
      }
    },
    "apiShareDetail": {
      "type": "object",
      "properties": {
        "resourceUrl": {
          "type": "string"
        },
        "source": {
          "type": "string",
          "format": "uint64"
        }
      }
    },
    "apiTags": {
      "type": "object",
      "properties": {
        "group_id": {
          "type": "string",
          "format": "uint64"
        },
        "creatorID": {
          "type": "string",
          "format": "uint64"
        },
        "name": {
          "type": "string"
        }
      }
    },
    "apiUnWatchProjectReqeust": {
      "type": "object",
      "properties": {
        "group_id": {
          "type": "string",
          "format": "uint64"
        },
        "project_id": {
          "type": "string",
          "format": "uint64"
        },
        "user_id": {
          "type": "string",
          "format": "uint64"
        }
      }
    },
    "apiUnWatchProjectResponse": {
      "type": "object"
    },
    "apiUpdateGroupInfoRequest": {
      "type": "object",
      "properties": {
        "group_id": {
          "type": "string",
          "format": "uint64"
        },
        "info": {
          "$ref": "#/definitions/apiGroupInfo"
        }
      }
    },
    "apiUpdateGroupInfoResponse": {
      "type": "object",
      "properties": {
        "info": {
          "$ref": "#/definitions/apiGroupInfo"
        }
      }
    },
    "apiUpdateItemRequest": {
      "type": "object",
      "properties": {
        "group_id": {
          "type": "string",
          "format": "uint64"
        },
        "project_id": {
          "type": "string",
          "format": "uint64"
        },
        "item_id": {
          "type": "string",
          "format": "uint64"
        },
        "info": {
          "$ref": "#/definitions/apiItemInfo"
        },
        "user_id": {
          "type": "string",
          "format": "uint64"
        }
      }
    },
    "apiUpdateItemResponse": {
      "type": "object",
      "properties": {
        "info": {
          "$ref": "#/definitions/apiItemInfo"
        }
      }
    },
    "apiUpdateProjectProfileRequest": {
      "type": "object",
      "properties": {
        "group_id": {
          "type": "string",
          "format": "uint64"
        },
        "project_id": {
          "type": "string",
          "format": "uint64"
        },
        "user_id": {
          "type": "string",
          "format": "uint64"
        },
        "info": {
          "$ref": "#/definitions/apiProjectProfileInfo"
        }
      }
    },
    "apiUpdateProjectProfileResponse": {
      "type": "object"
    },
    "apiUpdateProjectRequest": {
      "type": "object",
      "properties": {
        "group_id": {
          "type": "string",
          "format": "uint64"
        },
        "project_id": {
          "type": "string",
          "format": "uint64"
        },
        "user_id": {
          "type": "string",
          "format": "uint64"
        },
        "info": {
          "$ref": "#/definitions/apiProjectInfo"
        }
      }
    },
    "apiUpdateProjectResponse": {
      "type": "object",
      "properties": {
        "info": {
          "$ref": "#/definitions/apiProjectInfo"
        }
      }
    },
    "apiUpdateUserAvatorRequest": {
      "type": "object",
      "properties": {
        "user_id": {
          "type": "string",
          "format": "uint64"
        },
        "avatar": {
          "type": "string"
        }
      }
    },
    "apiUpdateUserAvatorResponse": {
      "type": "object",
      "properties": {
        "info": {
          "$ref": "#/definitions/apiUserInfo"
        }
      }
    },
    "apiUserFollowingGroupRequest": {
      "type": "object",
      "properties": {
        "user_id": {
          "type": "string",
          "format": "uint64"
        }
      }
    },
    "apiUserFollowingGroupResponse": {
      "type": "object",
      "properties": {
        "user_id": {
          "type": "string",
          "format": "uint64"
        },
        "list": {
          "type": "array",
          "items": {
            "$ref": "#/definitions/apiGroupInfo"
          }
        },
        "offset": {
          "type": "string",
          "format": "uint64"
        },
        "number": {
          "type": "string",
          "format": "uint64"
        }
      }
    },
    "apiUserGroupRequest": {
      "type": "object",
      "properties": {
        "user_id": {
          "type": "string",
          "format": "uint64"
        }
      }
    },
    "apiUserGroupResponse": {
      "type": "object",
      "properties": {
        "list": {
          "type": "array",
          "items": {
            "$ref": "#/definitions/apiGroupInfo"
          }
        }
      }
    },
    "apiUserInfo": {
      "type": "object",
      "properties": {
        "user_id": {
          "type": "string",
          "format": "uint64"
        },
        "name": {
          "type": "string"
        },
        "avatar": {
          "type": "string"
        },
        "email": {
          "type": "string"
        },
        "location": {
          "type": "string"
        },
        "desc": {
          "type": "string"
        }
      }
    },
    "apiUserInfoRequest": {
      "type": "object",
      "properties": {
        "user_id": {
          "type": "string",
          "format": "uint64"
        },
        "account": {
          "type": "string"
        }
      },
      "title": "user ,group .project.item"
    },
    "apiUserInfoResponse": {
      "type": "object",
      "properties": {
        "info": {
          "$ref": "#/definitions/apiUserInfo"
        }
      }
    },
    "apiUserUpdateRequest": {
      "type": "object",
      "properties": {
        "user_id": {
          "type": "string",
          "format": "uint64"
        },
        "nickname": {
          "type": "string"
        },
        "avatar": {
          "type": "string"
        },
        "desc": {
          "type": "string"
        }
      }
    },
    "apiUserUpdateResponse": {
      "type": "object"
    },
    "apiUserWatchingRequest": {
      "type": "object",
      "properties": {
        "user_id": {
          "type": "string",
          "format": "uint64"
        }
      }
    },
    "apiUserWatchingResponse": {
      "type": "object",
      "properties": {
        "list": {
          "type": "array",
          "items": {
            "$ref": "#/definitions/apiProjectInfo"
          }
        }
      }
    },
    "apiVersionResponse": {
      "type": "object",
      "properties": {
        "version": {
          "type": "string"
        }
      }
    },
    "apiVideoDetail": {
      "type": "object",
      "properties": {
        "list": {
          "type": "array",
          "items": {
            "$ref": "#/definitions/apiVideoInfo"
          }
        },
        "num": {
          "type": "string",
          "format": "uint64"
        }
      }
    },
    "apiVideoInfo": {
      "type": "object",
      "properties": {
        "resource_url": {
          "type": "string"
        },
        "size": {
          "type": "string",
          "format": "uint64"
        },
        "timeLength": {
          "type": "string",
          "format": "uint64"
        }
      }
    },
    "apiVisibleType": {
      "type": "string",
      "enum": [
        "AllPublic",
        "Public",
        "Private",
        "Someone"
      ],
      "default": "AllPublic"
    },
    "apiVoiceDetail": {
      "type": "object",
      "properties": {
        "resourceUrl": {
          "type": "string"
        },
        "size": {
          "type": "string",
          "format": "uint64"
        },
        "timeLength": {
          "type": "string",
          "format": "uint64"
        }
      }
    },
    "apiWatchProjectReqeust": {
      "type": "object",
      "properties": {
        "group_id": {
          "type": "string",
          "format": "uint64"
        },
        "project_id": {
          "type": "string",
          "format": "uint64"
        },
        "user_id": {
          "type": "string",
          "format": "uint64"
        }
      }
    },
    "apiWatchProjectResponse": {
      "type": "object"
    },
    "apiWordDetail": {
      "type": "object",
      "properties": {
        "content": {
          "type": "string"
        },
        "length": {
          "type": "string",
          "format": "uint64"
        }
      }
    }
  }
}
